src/fifo_mem.sv
module fifo_mem #(parameter DEPTH=8, DATA_WIDTH=8, PTR_WIDTH=3) (
  input logic wclk, w_en, rclk, r_en,
  input logic [PTR_WIDTH:0] b_wptr, b_rptr,
  input logic [DATA_WIDTH-1:0] data_in,
  input logic full, empty,
  output logic [DATA_WIDTH-1:0] data_out
);

  logic [DATA_WIDTH-1:0] fifo[0:DEPTH-1];
  
  always@(posedge wclk) begin
    if(w_en & !full) begin
      fifo[b_wptr[PTR_WIDTH-1:0]] <= data_in;
    end
  end
  
  always@(posedge rclk) begin
    if(r_en & !empty) begin
      data_out <= fifo[b_rptr[PTR_WIDTH-1:0]];
    end
  end
  
  // assign data_out = fifo[b_rptr[PTR_WIDTH-1:0]];
endmodule

src/rptr_handler.sv
module rptr_handler #(parameter PTR_WIDTH=3) (
  input logic rclk, rrst_n, r_en,
  input logic [PTR_WIDTH:0] g_wptr_sync,
  output logic [PTR_WIDTH:0] b_rptr, g_rptr,
  output logic empty
);

  logic [PTR_WIDTH:0] b_rptr_next;
  logic [PTR_WIDTH:0] g_rptr_next;

  assign b_rptr_next = b_rptr+(r_en & !empty);
  assign g_rptr_next = (b_rptr_next >>1)^b_rptr_next;
  assign rempty = (g_wptr_sync == g_rptr_next);

  // always@(posedge rclk or negedge rrst_n) begin
  //   if(!rrst_n) begin
  //     b_rptr_next <= 0;
  //     g_rptr_next <= 0;
  //   end
  //   else begin
  //     b_rptr_next <= b_rptr+(r_en & !empty);
  //     g_rptr_next <= (b_rptr_next >>1)^b_rptr_next;
  //   end
  // end
  
  always@(posedge rclk or negedge rrst_n) begin
    if(!rrst_n) begin
      b_rptr <= 0;
      g_rptr <= 0;
    end
    else begin
      b_rptr <= b_rptr_next;
      g_rptr <= g_rptr_next;
    end
  end
  
  always@(posedge rclk or negedge rrst_n) begin
    if(!rrst_n) empty <= 1;
    else        empty <= rempty;
  end
endmodule

src/wptr_handler.sv
module wptr_handler #(parameter PTR_WIDTH=3) (
  input logic wclk, wrst_n, w_en,
  input logic [PTR_WIDTH:0] g_rptr_sync,
  output logic [PTR_WIDTH:0] b_wptr, g_wptr,
  output logic full
);

  logic [PTR_WIDTH:0] b_wptr_next;
  logic [PTR_WIDTH:0] g_wptr_next;
   
  logic wrap_around;
  logic wfull;
  
  assign b_wptr_next = b_wptr+(w_en & !full);
  assign g_wptr_next = (b_wptr_next >>1)^b_wptr_next;
  
  always@(posedge wclk or negedge wrst_n) begin
    if(!wrst_n) begin
      b_wptr <= 0; // set default value
      g_wptr <= 0;
    end
    else begin
      b_wptr <= b_wptr_next; // incr binary write pointer
      g_wptr <= g_wptr_next; // incr gray write pointer
    end
  end
  
  always@(posedge wclk or negedge wrst_n) begin
    if(!wrst_n) full <= 0;
    else        full <= wfull;
  end

  assign wfull = (g_wptr_next == {~g_rptr_sync[PTR_WIDTH:PTR_WIDTH-1], g_rptr_sync[PTR_WIDTH-2:0]});

endmodule

src/synchronizer.sv
module synchronizer #(parameter WIDTH=3) (
  input logic clk, rst_n, [WIDTH:0] d_in, 
  output logic [WIDTH:0] d_out
  );
  
  logic [WIDTH:0] q1;

  always@(posedge clk, negedge rst_n) begin
    if(!rst_n) begin
      q1 <= 0;
      d_out <= 0;
    end
    else begin
      q1 <= d_in;
      d_out <= q1;
    end
  end
endmodule

src/asynchronous_fifo.sv
`include "synchronizer.sv"
`include "wptr_handler.sv"
`include "rptr_handler.sv"
`include "fifo_mem.sv"

module asynchronous_fifo #(parameter DEPTH=8, DATA_WIDTH=8) (
  input logic wclk, wrst_n,
  input logic rclk, rrst_n,
  input logic w_en, r_en,
  input logic [DATA_WIDTH-1:0] data_in,
  output logic [DATA_WIDTH-1:0] data_out,
  output logic full, empty
);
  
  parameter PTR_WIDTH = $clog2(DEPTH);
 
  logic [PTR_WIDTH:0] g_wptr_sync, g_rptr_sync;
  logic [PTR_WIDTH:0] b_wptr, b_rptr;
  logic [PTR_WIDTH:0] g_wptr, g_rptr;

  logic [PTR_WIDTH-1:0] waddr, raddr;

  synchronizer #(PTR_WIDTH) sync_wptr (rclk, rrst_n, g_wptr, g_wptr_sync); //write pointer to read clock domain
  synchronizer #(PTR_WIDTH) sync_rptr (wclk, wrst_n, g_rptr, g_rptr_sync); //read pointer to write clock domain 
  
  wptr_handler #(PTR_WIDTH) wptr_h(wclk, wrst_n, w_en,g_rptr_sync,b_wptr,g_wptr,full);
  rptr_handler #(PTR_WIDTH) rptr_h(rclk, rrst_n, r_en,g_wptr_sync,b_rptr,g_rptr,empty);
  fifo_mem fifom(wclk, w_en, rclk, r_en,b_wptr, b_rptr, data_in,full,empty, data_out);

endmodule

tb/async_fifo_tb.sv
module async_fifo_TB;

  parameter DATA_WIDTH = 8;

  logic [DATA_WIDTH-1:0] data_out, r_data_out;
  logic full;
  logic empty;
  logic [DATA_WIDTH-1:0] data_in;
  logic w_en, wclk, wrst_n;
  logic r_en, rclk, rrst_n;
  logic flag;

  // Queue to push data_in
  logic [DATA_WIDTH-1:0] wdata_q[$], wdata;

  asynchronous_fifo as_fifo (wclk, wrst_n,rclk, rrst_n,w_en,r_en,data_in,data_out,full,empty);

  always #10ns wclk = ~wclk;
  always #35ns rclk = ~rclk;
  
  initial begin
    wclk = 1'b0; wrst_n = 1'b0;
    w_en = 1'b0;
    data_in = 0;
    
    repeat(10) @(posedge wclk);
    wrst_n = 1'b1;

    repeat(2) begin
      for (int i=0; i<30; i++) begin
        @(posedge wclk iff !full);
        w_en = (i%2 == 0)? 1'b1 : 1'b0;
        if (w_en) begin
          data_in = $urandom;
          wdata_q.push_back(data_in);
        end
      end
      #50;
    end
  end

  initial begin
    rclk = 1'b0; rrst_n = 1'b0;
    r_en = 1'b0;
    flag = 0;

    repeat(20) @(posedge rclk);
    rrst_n = 1'b1;

    repeat(2) begin
      for (int i=0; i<30; i++) begin
        @(posedge rclk iff !empty);
        r_en = (i%2 == 1)? 1'b1 : 1'b0;
        if (r_en) begin
          // if(i == 1) @(posedge rclk iff !empty);
          if(flag!=0) wdata = wdata_q.pop_front();
          flag = 1;
          if(data_out !== wdata) $error("Time = %0t: Comparison Failed: expected wr_data = %h, rd_data = %h", $time, wdata, data_out);
          else $display("Time = %0t: Comparison Passed: wr_data = %h and rd_data = %h",$time, wdata, data_out);
        end
      end
      #50;
    end

    $finish;
  end
  
  initial begin 
    $dumpfile("dump.vcd"); $dumpvars;
  end
endmodule

sim/dump.vcd
$date
	Wed Apr 10 00:07:08 2024
$end
$version
	ModelSim Version 10.6
$end
$timescale
	1ns
$end

$scope module async_fifo_TB $end
$var reg 8 ! data_out [7:0] $end
$var reg 1 " full $end
$var reg 1 # empty $end
$var reg 8 $ data_in [7:0] $end
$var reg 1 % w_en $end
$var reg 1 & wclk $end
$var reg 1 ' wrst_n $end
$var reg 1 ( r_en $end
$var reg 1 ) rclk $end
$var reg 1 * rrst_n $end
$var reg 1 + flag $end
$var reg 8 , wdata [7:0] $end

$scope module as_fifo $end

$scope module fifom $end
$upscope $end
$upscope $end
$upscope $end

$scope begin std $end
$upscope $end
$enddefinitions $end
#0
$dumpvars
bx !
0"
1#
b0 $
0%
0&
0'
0(
0)
0*
0+
bx ,
$end
#10
1&
#20
0&
#30
1&
#35
1)
#40
0&
#50
1&
#60
0&
#70
0)
1&
#80
0&
#90
1&
#100
0&
#105
1)
#110
1&
#120
0&
#130
1&
#140
0)
0&
#150
1&
#160
0&
#170
1&
#175
1)
#180
0&
#190
1&
1'
#200
0&
#210
0)
1&
1%
b1110010 $
#220
0&
#230
1&
0%
#240
0&
#245
1)
#250
1&
1%
b10110010 $
#260
0&
#270
1&
0%
#280
0)
0&
#290
1&
1%
b10000 $
#300
0&
#310
1&
0%
#315
1)
#320
0&
#330
1&
1%
b110000 $
#340
0&
#350
0)
1&
0%
#360
0&
#370
1&
1%
b10110101 $
#380
0&
#385
1)
#390
1&
0%
#400
0&
#410
1&
1%
b10110110 $
#420
0)
0&
#430
1&
0%
#440
0&
#450
1&
1%
b10100 $
#455
1)
#460
0&
#470
1&
0%
#480
0&
#490
0)
1&
1%
b11011111 $
#500
0&
#510
1&
0%
1"
